{"metadata":null,"data":[{"name":"Sales","value":2.5,"variation":0.0,"currency":"$","displayOrder":1,"dataSeries":[{"date":"2025-12-14T23:45:00","value":0.0},{"date":"2025-12-15T03:30:00","value":0.0},{"date":"2025-12-15T12:00:00","value":0.0},{"date":"2025-12-15T18:15:00","value":1.2},{"date":"2025-12-15T18:30:00","value":1.3},{"date":"2025-12-15T18:45:00","value":2.0}]},{"name":"Sales Txns","value":10.0,"variation":0.0,"currency":"","displayOrder":2,"dataSeries":[{"date":"2025-12-14T23:45:00","value":0.0},{"date":"2025-12-15T03:30:00","value":0.0},{"date":"2025-12-15T12:00:00","value":0.0},{"date":"2025-12-15T18:15:00","value":8.0},{"date":"2025-12-15T18:30:00","value":2.0},{"date":"2025-12-15T18:45:00","value":2.0}]},{"name":"Total Owners","value":108697.0,"variation":0.0,"currency":"","displayOrder":3,"dataSeries":[{"date":"2025-12-14T23:45:00","value":108697.0},{"date":"2025-12-15T03:30:00","value":108697.0},{"date":"2025-12-15T12:00:00","value":108697.0},{"date":"2025-12-15T18:15:00","value":108697.0},{"date":"2025-12-15T18:30:00","value":108697.0},{"date":"2025-12-15T18:45:00","value":108697.0}]},{"name":"Average Hold","value":1157.12,"variation":0.0,"currency":"","displayOrder":4,"dataSeries":[{"date":"2025-12-14T23:45:00","value":0.0},{"date":"2025-12-15T03:30:00","value":0.0},{"date":"2025-12-15T12:00:00","value":0.0},{"date":"2025-12-15T18:15:00","value":1189.03},{"date":"2025-12-15T18:30:00","value":1029.49},{"date":"2025-12-15T18:45:00","value":1000.88}]},{"name":"Buyers","value":1.0,"variation":0.0,"currency":"","displayOrder":5,"dataSeries":[{"date":"2025-12-14T23:45:00","value":0.0},{"date":"2025-12-15T03:30:00","value":0.0},{"date":"2025-12-15T12:00:00","value":0.0},{"date":"2025-12-15T18:15:00","value":1.0},{"date":"2025-12-15T18:30:00","value":1.0},{"date":"2025-12-15T18:45:00","value":1.0}]},{"name":"Sellers","value":2.0,"variation":0.0,"currency":"","displayOrder":6,"dataSeries":[{"date":"2025-12-14T23:45:00","value":0.0},{"date":"2025-12-15T03:30:00","value":0.0},{"date":"2025-12-15T12:00:00","value":0.0},{"date":"2025-12-15T18:15:00","value":1.0},{"date":"2025-12-15T18:30:00","value":1.0},{"date":"2025-12-15T18:45:00","value":1.0}]}]}