{"metadata":null,"data":[{"name":"Sales","value":95.46,"variation":21.05,"currency":"$","displayOrder":1,"dataSeries":[{"date":"2026-01-12T04:00:00","value":2.99},{"date":"2026-01-12T07:45:00","value":2.78},{"date":"2026-01-12T08:00:00","value":13.52},{"date":"2026-01-12T16:15:00","value":0.0},{"date":"2026-01-12T18:30:00","value":11.94},{"date":"2026-01-12T18:45:00","value":11.72},{"date":"2026-01-12T21:00:00","value":18.11},{"date":"2026-01-12T21:15:00","value":7.96},{"date":"2026-01-12T21:30:00","value":13.93},{"date":"2026-01-12T21:45:00","value":5.56},{"date":"2026-01-12T22:00:00","value":6.95},{"date":"2026-01-12T22:15:00","value":0.0},{"date":"2026-01-12T22:30:00","value":0.0}]},{"name":"Sales Txns","value":55.0,"variation":17.33,"currency":"","displayOrder":2,"dataSeries":[{"date":"2026-01-12T04:00:00","value":1.0},{"date":"2026-01-12T07:45:00","value":2.0},{"date":"2026-01-12T08:00:00","value":8.0},{"date":"2026-01-12T16:15:00","value":0.0},{"date":"2026-01-12T18:30:00","value":6.0},{"date":"2026-01-12T18:45:00","value":8.0},{"date":"2026-01-12T21:00:00","value":10.0},{"date":"2026-01-12T21:15:00","value":4.0},{"date":"2026-01-12T21:30:00","value":7.0},{"date":"2026-01-12T21:45:00","value":4.0},{"date":"2026-01-12T22:00:00","value":5.0},{"date":"2026-01-12T22:15:00","value":0.0},{"date":"2026-01-12T22:30:00","value":0.0}]},{"name":"Total Owners","value":108697.0,"variation":0.0,"currency":"","displayOrder":3,"dataSeries":[{"date":"2026-01-12T04:00:00","value":108697.0},{"date":"2026-01-12T07:45:00","value":108697.0},{"date":"2026-01-12T08:00:00","value":108697.0},{"date":"2026-01-12T16:15:00","value":108697.0},{"date":"2026-01-12T18:30:00","value":108697.0},{"date":"2026-01-12T18:45:00","value":108697.0},{"date":"2026-01-12T21:00:00","value":108697.0},{"date":"2026-01-12T21:15:00","value":108697.0},{"date":"2026-01-12T21:30:00","value":108697.0},{"date":"2026-01-12T21:45:00","value":108697.0},{"date":"2026-01-12T22:00:00","value":108697.0},{"date":"2026-01-12T22:15:00","value":108697.0},{"date":"2026-01-12T22:30:00","value":108697.0}]},{"name":"Average Hold","value":340.96,"variation":0.15,"currency":"","displayOrder":4,"dataSeries":[{"date":"2026-01-12T04:00:00","value":152.05},{"date":"2026-01-12T07:45:00","value":338.66},{"date":"2026-01-12T08:00:00","value":338.19},{"date":"2026-01-12T16:15:00","value":0.0},{"date":"2026-01-12T18:30:00","value":305.09},{"date":"2026-01-12T18:45:00","value":338.84},{"date":"2026-01-12T21:00:00","value":408.67},{"date":"2026-01-12T21:15:00","value":338.66},{"date":"2026-01-12T21:30:00","value":312.06},{"date":"2026-01-12T21:45:00","value":339.01},{"date":"2026-01-12T22:00:00","value":339.01},{"date":"2026-01-12T22:15:00","value":0.0},{"date":"2026-01-12T22:30:00","value":0.0}]},{"name":"Buyers","value":3.0,"variation":0.5,"currency":"","displayOrder":5,"dataSeries":[{"date":"2026-01-12T04:00:00","value":1.0},{"date":"2026-01-12T07:45:00","value":1.0},{"date":"2026-01-12T08:00:00","value":1.0},{"date":"2026-01-12T16:15:00","value":0.0},{"date":"2026-01-12T18:30:00","value":1.0},{"date":"2026-01-12T18:45:00","value":1.0},{"date":"2026-01-12T21:00:00","value":2.0},{"date":"2026-01-12T21:15:00","value":1.0},{"date":"2026-01-12T21:30:00","value":1.0},{"date":"2026-01-12T21:45:00","value":1.0},{"date":"2026-01-12T22:00:00","value":1.0},{"date":"2026-01-12T22:15:00","value":0.0},{"date":"2026-01-12T22:30:00","value":0.0}]},{"name":"Sellers","value":2.0,"variation":0.0,"currency":"","displayOrder":6,"dataSeries":[{"date":"2026-01-12T04:00:00","value":1.0},{"date":"2026-01-12T07:45:00","value":1.0},{"date":"2026-01-12T08:00:00","value":1.0},{"date":"2026-01-12T16:15:00","value":0.0},{"date":"2026-01-12T18:30:00","value":1.0},{"date":"2026-01-12T18:45:00","value":1.0},{"date":"2026-01-12T21:00:00","value":2.0},{"date":"2026-01-12T21:15:00","value":1.0},{"date":"2026-01-12T21:30:00","value":1.0},{"date":"2026-01-12T21:45:00","value":1.0},{"date":"2026-01-12T22:00:00","value":1.0},{"date":"2026-01-12T22:15:00","value":0.0},{"date":"2026-01-12T22:30:00","value":0.0}]}]}