{"metadata":null,"data":[{"name":"Sales","value":42.19,"variation":20.10,"currency":"$","displayOrder":1,"dataSeries":[{"date":"2025-12-26T17:00:00","value":6.26},{"date":"2025-12-26T18:15:00","value":2.0},{"date":"2025-12-26T20:15:00","value":1.0},{"date":"2025-12-26T20:30:00","value":0.0},{"date":"2025-12-26T21:15:00","value":0.0},{"date":"2025-12-26T22:00:00","value":0.0},{"date":"2025-12-26T22:45:00","value":0.0},{"date":"2025-12-26T23:30:00","value":0.0},{"date":"2025-12-27T02:00:00","value":2.95},{"date":"2025-12-27T02:15:00","value":3.49},{"date":"2025-12-27T05:30:00","value":3.75},{"date":"2025-12-27T06:00:00","value":7.89},{"date":"2025-12-27T06:15:00","value":12.35},{"date":"2025-12-27T06:30:00","value":2.5}]},{"name":"Sales Txns","value":32.0,"variation":31.0,"currency":"","displayOrder":2,"dataSeries":[{"date":"2025-12-26T17:00:00","value":5.0},{"date":"2025-12-26T18:15:00","value":1.0},{"date":"2025-12-26T20:15:00","value":2.0},{"date":"2025-12-26T20:30:00","value":0.0},{"date":"2025-12-26T21:15:00","value":0.0},{"date":"2025-12-26T22:00:00","value":0.0},{"date":"2025-12-26T22:45:00","value":0.0},{"date":"2025-12-26T23:30:00","value":0.0},{"date":"2025-12-27T02:00:00","value":3.0},{"date":"2025-12-27T02:15:00","value":2.0},{"date":"2025-12-27T05:30:00","value":3.0},{"date":"2025-12-27T06:00:00","value":4.0},{"date":"2025-12-27T06:15:00","value":10.0},{"date":"2025-12-27T06:30:00","value":2.0}]},{"name":"Total Owners","value":108697.0,"variation":0.0,"currency":"","displayOrder":3,"dataSeries":[{"date":"2025-12-26T17:00:00","value":108697.0},{"date":"2025-12-26T18:15:00","value":108697.0},{"date":"2025-12-26T20:15:00","value":108697.0},{"date":"2025-12-26T20:30:00","value":108697.0},{"date":"2025-12-26T21:15:00","value":108697.0},{"date":"2025-12-26T22:00:00","value":108697.0},{"date":"2025-12-26T22:45:00","value":108697.0},{"date":"2025-12-26T23:30:00","value":108697.0},{"date":"2025-12-27T02:00:00","value":108697.0},{"date":"2025-12-27T02:15:00","value":108697.0},{"date":"2025-12-27T05:30:00","value":108697.0},{"date":"2025-12-27T06:00:00","value":108697.0},{"date":"2025-12-27T06:15:00","value":108697.0},{"date":"2025-12-27T06:30:00","value":108697.0}]},{"name":"Average Hold","value":468.67,"variation":-2.00,"currency":"","displayOrder":4,"dataSeries":[{"date":"2025-12-26T17:00:00","value":536.76},{"date":"2025-12-26T18:15:00","value":1192.02},{"date":"2025-12-26T20:15:00","value":1418.78},{"date":"2025-12-26T20:30:00","value":0.0},{"date":"2025-12-26T21:15:00","value":0.0},{"date":"2025-12-26T22:00:00","value":0.0},{"date":"2025-12-26T22:45:00","value":0.0},{"date":"2025-12-26T23:30:00","value":0.0},{"date":"2025-12-27T02:00:00","value":194.76},{"date":"2025-12-27T02:15:00","value":128.56},{"date":"2025-12-27T05:30:00","value":338.64},{"date":"2025-12-27T06:00:00","value":603.35},{"date":"2025-12-27T06:15:00","value":334.37},{"date":"2025-12-27T06:30:00","value":334.82}]},{"name":"Buyers","value":3.0,"variation":2.0,"currency":"","displayOrder":5,"dataSeries":[{"date":"2025-12-26T17:00:00","value":1.0},{"date":"2025-12-26T18:15:00","value":1.0},{"date":"2025-12-26T20:15:00","value":1.0},{"date":"2025-12-26T20:30:00","value":0.0},{"date":"2025-12-26T21:15:00","value":0.0},{"date":"2025-12-26T22:00:00","value":0.0},{"date":"2025-12-26T22:45:00","value":0.0},{"date":"2025-12-26T23:30:00","value":0.0},{"date":"2025-12-27T02:00:00","value":1.0},{"date":"2025-12-27T02:15:00","value":1.0},{"date":"2025-12-27T05:30:00","value":1.0},{"date":"2025-12-27T06:00:00","value":1.0},{"date":"2025-12-27T06:15:00","value":1.0},{"date":"2025-12-27T06:30:00","value":1.0}]},{"name":"Sellers","value":3.0,"variation":2.0,"currency":"","displayOrder":6,"dataSeries":[{"date":"2025-12-26T17:00:00","value":1.0},{"date":"2025-12-26T18:15:00","value":1.0},{"date":"2025-12-26T20:15:00","value":1.0},{"date":"2025-12-26T20:30:00","value":0.0},{"date":"2025-12-26T21:15:00","value":0.0},{"date":"2025-12-26T22:00:00","value":0.0},{"date":"2025-12-26T22:45:00","value":0.0},{"date":"2025-12-26T23:30:00","value":0.0},{"date":"2025-12-27T02:00:00","value":1.0},{"date":"2025-12-27T02:15:00","value":1.0},{"date":"2025-12-27T05:30:00","value":1.0},{"date":"2025-12-27T06:00:00","value":2.0},{"date":"2025-12-27T06:15:00","value":1.0},{"date":"2025-12-27T06:30:00","value":1.0}]}]}