{"metadata":null,"data":[{"name":"Sales","value":75.85,"variation":0.0,"currency":"$","displayOrder":1,"dataSeries":[{"date":"2026-02-20T16:30:00","value":5.85},{"date":"2026-02-21T07:15:00","value":35.0},{"date":"2026-02-21T07:30:00","value":0.0}]},{"name":"Sales Txns","value":5.0,"variation":0.0,"currency":"","displayOrder":2,"dataSeries":[{"date":"2026-02-20T16:30:00","value":1.0},{"date":"2026-02-21T07:15:00","value":3.0},{"date":"2026-02-21T07:30:00","value":0.0}]},{"name":"Total Owners","value":108697.0,"variation":0.0,"currency":"","displayOrder":3,"dataSeries":[{"date":"2026-02-20T16:30:00","value":108697.0},{"date":"2026-02-21T07:15:00","value":108697.0},{"date":"2026-02-21T07:30:00","value":108697.0}]},{"name":"Average Hold","value":771.21,"variation":0.0,"currency":"","displayOrder":4,"dataSeries":[{"date":"2026-02-20T16:30:00","value":1290.87},{"date":"2026-02-21T07:15:00","value":437.14},{"date":"2026-02-21T07:30:00","value":0.0}]},{"name":"Buyers","value":3.0,"variation":0.0,"currency":"","displayOrder":5,"dataSeries":[{"date":"2026-02-20T16:30:00","value":1.0},{"date":"2026-02-21T07:15:00","value":1.0},{"date":"2026-02-21T07:30:00","value":0.0}]},{"name":"Sellers","value":1.0,"variation":0.0,"currency":"","displayOrder":6,"dataSeries":[{"date":"2026-02-20T16:30:00","value":1.0},{"date":"2026-02-21T07:15:00","value":1.0},{"date":"2026-02-21T07:30:00","value":0.0}]}]}