{"metadata":null,"data":[{"name":"Sales","value":10.99,"variation":0.0,"currency":"$","displayOrder":1,"dataSeries":[{"date":"2025-09-02T06:45:00","value":0.0},{"date":"2025-09-02T08:00:00","value":0.0},{"date":"2025-09-02T10:15:00","value":0.0},{"date":"2025-09-02T17:45:00","value":0.0},{"date":"2025-09-02T18:30:00","value":0.0},{"date":"2025-09-02T22:00:00","value":3.99},{"date":"2025-09-02T22:15:00","value":5.0},{"date":"2025-09-02T22:30:00","value":2.0},{"date":"2025-09-02T23:30:00","value":0.0},{"date":"2025-09-03T00:30:00","value":0.0},{"date":"2025-09-03T01:00:00","value":0.0},{"date":"2025-09-03T03:15:00","value":0.0},{"date":"2025-09-03T03:45:00","value":90.0},{"date":"2025-09-03T06:00:00","value":0.0}]},{"name":"Sales Txns","value":11.0,"variation":0.0,"currency":"","displayOrder":2,"dataSeries":[{"date":"2025-09-02T06:45:00","value":0.0},{"date":"2025-09-02T08:00:00","value":0.0},{"date":"2025-09-02T10:15:00","value":0.0},{"date":"2025-09-02T17:45:00","value":0.0},{"date":"2025-09-02T18:30:00","value":0.0},{"date":"2025-09-02T22:00:00","value":5.0},{"date":"2025-09-02T22:15:00","value":5.0},{"date":"2025-09-02T22:30:00","value":2.0},{"date":"2025-09-02T23:30:00","value":0.0},{"date":"2025-09-03T00:30:00","value":0.0},{"date":"2025-09-03T01:00:00","value":0.0},{"date":"2025-09-03T03:15:00","value":0.0},{"date":"2025-09-03T03:45:00","value":1.0},{"date":"2025-09-03T06:00:00","value":0.0}]},{"name":"Total Owners","value":108697.0,"variation":0.0,"currency":"","displayOrder":3,"dataSeries":[{"date":"2025-09-02T06:45:00","value":108697.0},{"date":"2025-09-02T08:00:00","value":108697.0},{"date":"2025-09-02T10:15:00","value":108697.0},{"date":"2025-09-02T17:45:00","value":108697.0},{"date":"2025-09-02T18:30:00","value":108697.0},{"date":"2025-09-02T22:00:00","value":108697.0},{"date":"2025-09-02T22:15:00","value":108697.0},{"date":"2025-09-02T22:30:00","value":108697.0},{"date":"2025-09-02T23:30:00","value":108697.0},{"date":"2025-09-03T00:30:00","value":108697.0},{"date":"2025-09-03T01:00:00","value":108697.0},{"date":"2025-09-03T03:15:00","value":108697.0},{"date":"2025-09-03T03:45:00","value":108697.0},{"date":"2025-09-03T06:00:00","value":108697.0}]},{"name":"Average Hold","value":346.12,"variation":0.0,"currency":"","displayOrder":4,"dataSeries":[{"date":"2025-09-02T06:45:00","value":0.0},{"date":"2025-09-02T08:00:00","value":0.0},{"date":"2025-09-02T10:15:00","value":0.0},{"date":"2025-09-02T17:45:00","value":0.0},{"date":"2025-09-02T18:30:00","value":0.0},{"date":"2025-09-02T22:00:00","value":136.80},{"date":"2025-09-02T22:15:00","value":543.89},{"date":"2025-09-02T22:30:00","value":201.92},{"date":"2025-09-02T23:30:00","value":0.0},{"date":"2025-09-03T00:30:00","value":0.0},{"date":"2025-09-03T01:00:00","value":0.0},{"date":"2025-09-03T03:15:00","value":0.0},{"date":"2025-09-03T03:45:00","value":147.01},{"date":"2025-09-03T06:00:00","value":0.0}]},{"name":"Buyers","value":2.0,"variation":0.0,"currency":"","displayOrder":5,"dataSeries":[{"date":"2025-09-02T06:45:00","value":0.0},{"date":"2025-09-02T08:00:00","value":0.0},{"date":"2025-09-02T10:15:00","value":0.0},{"date":"2025-09-02T17:45:00","value":0.0},{"date":"2025-09-02T18:30:00","value":0.0},{"date":"2025-09-02T22:00:00","value":1.0},{"date":"2025-09-02T22:15:00","value":1.0},{"date":"2025-09-02T22:30:00","value":1.0},{"date":"2025-09-02T23:30:00","value":0.0},{"date":"2025-09-03T00:30:00","value":0.0},{"date":"2025-09-03T01:00:00","value":0.0},{"date":"2025-09-03T03:15:00","value":0.0},{"date":"2025-09-03T03:45:00","value":1.0},{"date":"2025-09-03T06:00:00","value":0.0}]},{"name":"Sellers","value":3.0,"variation":0.0,"currency":"","displayOrder":6,"dataSeries":[{"date":"2025-09-02T06:45:00","value":0.0},{"date":"2025-09-02T08:00:00","value":0.0},{"date":"2025-09-02T10:15:00","value":0.0},{"date":"2025-09-02T17:45:00","value":0.0},{"date":"2025-09-02T18:30:00","value":0.0},{"date":"2025-09-02T22:00:00","value":2.0},{"date":"2025-09-02T22:15:00","value":1.0},{"date":"2025-09-02T22:30:00","value":1.0},{"date":"2025-09-02T23:30:00","value":0.0},{"date":"2025-09-03T00:30:00","value":0.0},{"date":"2025-09-03T01:00:00","value":0.0},{"date":"2025-09-03T03:15:00","value":0.0},{"date":"2025-09-03T03:45:00","value":1.0},{"date":"2025-09-03T06:00:00","value":0.0}]}]}